MANIFEST.in
README.rst
setup.py
movementtypes/__init__.py
movementtypes/cli.py
movementtypes/movementtypes.py
movementtypes/sskernel.py
movementtypes.egg-info/PKG-INFO
movementtypes.egg-info/SOURCES.txt
movementtypes.egg-info/dependency_links.txt
movementtypes.egg-info/entry_points.txt
movementtypes.egg-info/not-zip-safe
movementtypes.egg-info/requires.txt
movementtypes.egg-info/top_level.txt
tests/__init__.py
tests/test_mvtypes.py