Metadata-Version: 1.0
Name: movementtypes
Version: 0.1.1
Summary: extract GPS traces from file and analyze them to reveal movement types
Home-page: https://github.com/gipong/movementtypes.git
Author: Huang-Sin Syu, Tyng-Ruey Chuang
Author-email: sheu781230@gmail.com, trc@iis.sinica.edu.tw
License: MIT
Platform: UNKNOWN
